langchain_azure_storage/__init__.py
langchain_azure_storage/document_loaders.py
langchain_azure_storage-1.0.0.dist-info/LICENSE
langchain_azure_storage-1.0.0.dist-info/METADATA
langchain_azure_storage-1.0.0.dist-info/WHEEL
langchain_azure_storage-1.0.0.dist-info/RECORD
