Metadata-Version: 2.3
Name: langchain-azure-storage
Version: 1.0.0
Summary: LangChain integrations for Azure Storage
License: MIT License
Keywords: langchain,azure
Author: Microsoft Corporation
Author-email: ascl@microsoft.com
Requires-Python: ~=3.10
Classifier: Development Status :: 4 - Beta
Classifier: License :: OSI Approved :: MIT License
Classifier: Programming Language :: Python
Classifier: Programming Language :: Python :: 3
Classifier: Programming Language :: Python :: 3 :: Only
Classifier: Programming Language :: Python :: 3.10
Classifier: Programming Language :: Python :: 3.11
Classifier: Programming Language :: Python :: 3.12
Classifier: Programming Language :: Python :: 3.13
Requires-Dist: azure-identity (>=1.25,<2.0)
Requires-Dist: azure-storage-blob[aio] (>=12.26,<13.0)
Requires-Dist: langchain-core (>=1.0,<2.0)
Project-URL: Repository, https://github.com/langchain-ai/langchain-azure
Project-URL: Release Notes, https://github.com/langchain-ai/langchain-azure/releases
Project-URL: Source Code, https://github.com/langchain-ai/langchain-azure/tree/main/libs/azure-storage
